{
  "id": "value-price-profit",
  "title": "Value, Price and Profit",
  "authors": [
    "Karl Marx"
  ],
  "year": 1865,
  "source": "Wikisource",
  "source_url": "https://en.wikisource.org/wiki/Wages,_Price_and_Profit",
  "license": "Public domain",
  "translator": null,
  "aliases": [
    "value price profit",
    "value price and profit",
    "wages price and profit"
  ],
  "description": "An 1865 address to the First International in which Marx argues that wage increases do not cause price inflation, developing the labour theory of value."
}
